<?xml version="1.0"?>
<MarketData>
    <success>true</success>
    <message>Loaded</message>
    <data>
        <Stock>
            <company>Wal-Mart Stores, Inc.</company>
            <symbol>WMT</symbol>
            <exchange>NYSE</exchange>
            <lastPrice>68.85</lastPrice>
            <change>-0.36</change>
            <quantity>89.00</quantity>
            <costBasis>6088.9</costBasis>
            <marketValue>6127.65</marketValue>
            <gain>38.75</gain>
            <gainPercentage>0.64</gainPercentage>
            <dailyGain>-32.040089</dailyGain>
            <overallReturn>0.64</overallReturn>
            <marketCap>230319.62</marketCap>
            <openPrice>69.3</openPrice>
            <dailyHighPrice>69.3199</dailyHighPrice>
            <dailyLowPrice>68.71</dailyLowPrice>
            <averageVolume>8.8821287</averageVolume>
            <weekHigh52>77.6</weekHigh52>
            <weekLow52>57.18</weekLow52>
            <earningsPerShare>4.85919</earningsPerShare>
            <priceEarningsRatio>14.17</priceEarningsRatio>
            <beta>0.33</beta>
            <return1week>0.64</return1week>
            <return4week>0.64</return4week>
            <return3month>0.64</return3month>
            <returnYeartodate>0.64</returnYeartodate>
            <return1year>0.64</return1year>
            <return3year>0.64</return3year>
            <return5year>0.64</return5year>
            <changePercentage>-0.52015692</changePercentage>
            <sector>Services</sector>
            <industry>Retail (Department and Discount)</industry>
            <volume>7.2335491</volume>
        </Stock>
        <Stock>
            <company>Verizon Communications...</company>
            <symbol>VZ</symbol>
            <exchange>NYSE</exchange>
            <lastPrice>42.13</lastPrice>
            <change>0.62</change>
            <quantity>103.00</quantity>
            <costBasis>4393.37</costBasis>
            <marketValue>4339.39</marketValue>
            <gain>-53.98</gain>
            <gainPercentage>-1.23</gainPercentage>
            <dailyGain>63.86031</dailyGain>
            <overallReturn>-1.23</overallReturn>
            <marketCap>120235.64</marketCap>
            <openPrice>41.6601</openPrice>
            <dailyHighPrice>42.37</dailyHighPrice>
            <dailyLowPrice>41.51</dailyLowPrice>
            <averageVolume>13.233866</averageVolume>
            <weekHigh52>48.77</weekHigh52>
            <weekLow52>36.8</weekLow52>
            <earningsPerShare>1.0726</earningsPerShare>
            <priceEarningsRatio>39.28</priceEarningsRatio>
            <beta>0.49</beta>
            <return1week>-1.23</return1week>
            <return4week>-1.23</return4week>
            <return3month>-1.23</return3month>
            <returnYeartodate>-1.23</returnYeartodate>
            <return1year>-1.23</return1year>
            <return3year>-1.23</return3year>
            <return5year>-1.23</return5year>
            <changePercentage>1.4936227</changePercentage>
            <sector>Services</sector>
            <industry>Communications Services</industry>
            <volume>14.210915</volume>
        </Stock>
        <Stock>
            <company>United Technologies...</company>
            <symbol>UTX</symbol>
            <exchange>NYSE</exchange>
            <lastPrice>86.4</lastPrice>
            <change>0.83</change>
            <quantity>86.00</quantity>
            <costBasis>7345.47</costBasis>
            <marketValue>7430.4</marketValue>
            <gain>84.93</gain>
            <gainPercentage>1.16</gainPercentage>
            <dailyGain>71.380173</dailyGain>
            <overallReturn>1.16</overallReturn>
            <marketCap>79189.445</marketCap>
            <openPrice>86.08</openPrice>
            <dailyHighPrice>86.5999</dailyHighPrice>
            <dailyLowPrice>85.59</dailyLowPrice>
            <averageVolume>3.8598471</averageVolume>
            <weekHigh52>87.5</weekHigh52>
            <weekLow52>70.71</weekLow52>
            <earningsPerShare>5.78408</earningsPerShare>
            <priceEarningsRatio>14.94</priceEarningsRatio>
            <beta>1.05</beta>
            <return1week>1.16</return1week>
            <return4week>1.16</return4week>
            <return3month>1.16</return3month>
            <returnYeartodate>1.16</returnYeartodate>
            <return1year>1.16</return1year>
            <return3year>1.16</return3year>
            <return5year>1.16</return5year>
            <changePercentage>0.96996826</changePercentage>
            <sector>Capital Goods</sector>
            <industry>Aerospace and Defense</industry>
            <volume>3.430738</volume>
        </Stock>
        <Stock>
            <company>The Procter &amp; Gamble...</company>
            <symbol>PG</symbol>
            <exchange>NYSE</exchange>
            <lastPrice>69.67</lastPrice>
            <change>0.33</change>
            <quantity>52.00</quantity>
            <costBasis>3616.31</costBasis>
            <marketValue>3622.84</marketValue>
            <gain>6.53</gain>
            <gainPercentage>0.18</gainPercentage>
            <dailyGain>17.160105</dailyGain>
            <overallReturn>0.18</overallReturn>
            <marketCap>190493.84</marketCap>
            <openPrice>69.56</openPrice>
            <dailyHighPrice>69.96</dailyHighPrice>
            <dailyLowPrice>69.34</dailyLowPrice>
            <averageVolume>8.91392</averageVolume>
            <weekHigh52>70.99</weekHigh52>
            <weekLow52>59.07</weekLow52>
            <earningsPerShare>3.06497</earningsPerShare>
            <priceEarningsRatio>22.73</priceEarningsRatio>
            <beta>0.46</beta>
            <return1week>0.18</return1week>
            <return4week>0.18</return4week>
            <return3month>0.18</return3month>
            <returnYeartodate>0.18</returnYeartodate>
            <return1year>0.18</return1year>
            <return3year>0.18</return3year>
            <return5year>0.18</return5year>
            <changePercentage>0.47591844</changePercentage>
            <sector>Consumer/Non-Cyclical</sector>
            <industry>Personal and Household Prods.</industry>
            <volume>6.271801</volume>
        </Stock>
        <Stock>
            <company>The Home Depot, Inc.</company>
            <symbol>HD</symbol>
            <exchange>NYSE</exchange>
            <lastPrice>65.05</lastPrice>
            <change>1.19</change>
            <quantity>51.00</quantity>
            <costBasis>3258.49</costBasis>
            <marketValue>3317.55</marketValue>
            <gain>59.06</gain>
            <gainPercentage>1.81</gainPercentage>
            <dailyGain>60.6901</dailyGain>
            <overallReturn>1.81</overallReturn>
            <marketCap>97261.43</marketCap>
            <openPrice>64.19</openPrice>
            <dailyHighPrice>65.29</dailyHighPrice>
            <dailyLowPrice>64.04</dailyLowPrice>
            <averageVolume>6.5694609</averageVolume>
            <weekHigh52>65.92</weekHigh52>
            <weekLow52>43.7</weekLow52>
            <earningsPerShare>2.82567</earningsPerShare>
            <priceEarningsRatio>23.02</priceEarningsRatio>
            <beta>0.81</beta>
            <return1week>1.81</return1week>
            <return4week>1.81</return4week>
            <return3month>1.81</return3month>
            <returnYeartodate>1.81</returnYeartodate>
            <return1year>1.81</return1year>
            <return3year>1.81</return3year>
            <return5year>1.81</return5year>
            <changePercentage>1.8634551</changePercentage>
            <sector>Services</sector>
            <industry>Retail (Home Improvement)</industry>
            <volume>7.797153</volume>
        </Stock>
        <Stock>
            <company>The Coca-Cola Company</company>
            <symbol>KO</symbol>
            <exchange>NYSE</exchange>
            <lastPrice>37.51</lastPrice>
            <change>0.19</change>
            <quantity>130.00</quantity>
            <costBasis>4828.69</costBasis>
            <marketValue>4876.3</marketValue>
            <gain>47.61</gain>
            <gainPercentage>0.99</gainPercentage>
            <dailyGain>24.699869</dailyGain>
            <overallReturn>0.99</overallReturn>
            <marketCap>168238.41</marketCap>
            <openPrice>37.43</openPrice>
            <dailyHighPrice>37.66</dailyHighPrice>
            <dailyLowPrice>37.33</dailyLowPrice>
            <averageVolume>13.799459</averageVolume>
            <weekHigh52>40.665</weekHigh52>
            <weekLow52>33.515</weekLow52>
            <earningsPerShare>1.91592</earningsPerShare>
            <priceEarningsRatio>19.58</priceEarningsRatio>
            <beta>0.51</beta>
            <return1week>0.99</return1week>
            <return4week>0.99</return4week>
            <return3month>0.99</return3month>
            <returnYeartodate>0.99</returnYeartodate>
            <return1year>0.99</return1year>
            <return3year>0.99</return3year>
            <return5year>0.99</return5year>
            <changePercentage>0.5091067</changePercentage>
            <sector>Consumer/Non-Cyclical</sector>
            <industry>Beverages (Nonalcoholic)</industry>
            <volume>12.122702</volume>
        </Stock>
        <Stock>
            <company>Pfizer Inc.</company>
            <symbol>PFE</symbol>
            <exchange>NYSE</exchange>
            <lastPrice>26.83</lastPrice>
            <change>0.22</change>
            <quantity>98.00</quantity>
            <costBasis>2625.81</costBasis>
            <marketValue>2629.34</marketValue>
            <gain>3.53</gain>
            <gainPercentage>0.13</gainPercentage>
            <dailyGain>21.559902</dailyGain>
            <overallReturn>0.13</overallReturn>
            <marketCap>197537.84</marketCap>
            <openPrice>26.75</openPrice>
            <dailyHighPrice>26.96</dailyHighPrice>
            <dailyLowPrice>26.63</dailyLowPrice>
            <averageVolume>30.0103</averageVolume>
            <weekHigh52>26.96</weekHigh52>
            <weekLow52>20.75</weekLow52>
            <earningsPerShare>1.2519</earningsPerShare>
            <priceEarningsRatio>21.43</priceEarningsRatio>
            <beta>0.68</beta>
            <return1week>0.13</return1week>
            <return4week>0.13</return4week>
            <return3month>0.13</return3month>
            <returnYeartodate>0.13</returnYeartodate>
            <return1year>0.13</return1year>
            <return3year>0.13</return3year>
            <return5year>0.13</return5year>
            <changePercentage>0.82675427</changePercentage>
            <sector>Healthcare</sector>
            <industry>Major Drugs</industry>
            <volume>37.12262</volume>
        </Stock>
        <Stock>
            <company>Microsoft Corporation</company>
            <symbol>MSFT</symbol>
            <exchange>NASDAQ</exchange>
            <lastPrice>27.25</lastPrice>
            <change>0.21</change>
            <quantity>62.00</quantity>
            <costBasis>1683.45</costBasis>
            <marketValue>1689.5</marketValue>
            <gain>6.05</gain>
            <gainPercentage>0.36</gainPercentage>
            <dailyGain>13.019938</dailyGain>
            <overallReturn>0.36</overallReturn>
            <marketCap>229348.61</marketCap>
            <openPrice>27.19</openPrice>
            <dailyHighPrice>27.47</dailyHighPrice>
            <dailyLowPrice>27.06</dailyLowPrice>
            <averageVolume>48.114334</averageVolume>
            <weekHigh52>32.95</weekHigh52>
            <weekLow52>26.26</weekLow52>
            <earningsPerShare>1.85072</earningsPerShare>
            <priceEarningsRatio>14.72</priceEarningsRatio>
            <beta>0.97</beta>
            <return1week>0.36</return1week>
            <return4week>0.36</return4week>
            <return3month>0.36</return3month>
            <returnYeartodate>0.36</returnYeartodate>
            <return1year>0.36</return1year>
            <return3year>0.36</return3year>
            <return5year>0.36</return5year>
            <changePercentage>0.77662379</changePercentage>
            <sector>Technology</sector>
            <industry>Software and Programming</industry>
            <volume>51.685841</volume>
        </Stock>
        <Stock>
            <company>Merck &amp; Co., Inc.</company>
            <symbol>MRK</symbol>
            <exchange>NYSE</exchange>
            <lastPrice>42.75</lastPrice>
            <change>0.21</change>
            <quantity>65.00</quantity>
            <costBasis>2839.69</costBasis>
            <marketValue>2778.75</marketValue>
            <gain>-60.94</gain>
            <gainPercentage>-2.15</gainPercentage>
            <dailyGain>13.649935</dailyGain>
            <overallReturn>-2.15</overallReturn>
            <marketCap>129963.08</marketCap>
            <openPrice>42.81</openPrice>
            <dailyHighPrice>42.85</dailyHighPrice>
            <dailyLowPrice>42.5375</dailyLowPrice>
            <averageVolume>13.427018</averageVolume>
            <weekHigh52>48</weekHigh52>
            <weekLow52>36.91</weekLow52>
            <earningsPerShare>2.20127</earningsPerShare>
            <priceEarningsRatio>19.42</priceEarningsRatio>
            <beta>0.30</beta>
            <return1week>-2.15</return1week>
            <return4week>-2.15</return4week>
            <return3month>-2.15</return3month>
            <returnYeartodate>-2.15</returnYeartodate>
            <return1year>-2.15</return1year>
            <return3year>-2.15</return3year>
            <return5year>-2.15</return5year>
            <changePercentage>0.49365088</changePercentage>
            <sector>Healthcare</sector>
            <industry>Biotechnology and Drugs</industry>
            <volume>15.520213</volume>
        </Stock>
        <Stock>
            <company>McDonald&apos;s Corporation</company>
            <symbol>MCD</symbol>
            <exchange>NYSE</exchange>
            <lastPrice>91.76</lastPrice>
            <change>0.66</change>
            <quantity>34.00</quantity>
            <costBasis>3117.73</costBasis>
            <marketValue>3119.84</marketValue>
            <gain>2.11</gain>
            <gainPercentage>0.07</gainPercentage>
            <dailyGain>22.440136</dailyGain>
            <overallReturn>0.07</overallReturn>
            <marketCap>92124.9</marketCap>
            <openPrice>91.45</openPrice>
            <dailyHighPrice>92.1</dailyHighPrice>
            <dailyLowPrice>91.31</dailyLowPrice>
            <averageVolume>5.3778348</averageVolume>
            <weekHigh52>102.22</weekHigh52>
            <weekLow52>83.31</weekLow52>
            <earningsPerShare>5.30873</earningsPerShare>
            <priceEarningsRatio>17.28</priceEarningsRatio>
            <beta>0.39</beta>
            <return1week>0.07</return1week>
            <return4week>0.07</return4week>
            <return3month>0.07</return3month>
            <returnYeartodate>0.07</returnYeartodate>
            <return1year>0.07</return1year>
            <return3year>0.07</return3year>
            <return5year>0.07</return5year>
            <changePercentage>0.72448266</changePercentage>
            <sector>Services</sector>
            <industry>Restaurants</industry>
            <volume>4.0454421</volume>
        </Stock>
        <Stock>
            <company>JPMorgan Chase &amp; Co.</company>
            <symbol>JPM</symbol>
            <exchange>NYSE</exchange>
            <lastPrice>46.44</lastPrice>
            <change>-0.38</change>
            <quantity>121.00</quantity>
            <costBasis>5524.28</costBasis>
            <marketValue>5619.24</marketValue>
            <gain>94.96</gain>
            <gainPercentage>1.72</gainPercentage>
            <dailyGain>-45.980122</dailyGain>
            <overallReturn>1.72</overallReturn>
            <marketCap>176657.75</marketCap>
            <openPrice>46.4</openPrice>
            <dailyHighPrice>46.87</dailyHighPrice>
            <dailyLowPrice>46.29</dailyLowPrice>
            <averageVolume>24.264896</averageVolume>
            <weekHigh52>46.87</weekHigh52>
            <weekLow52>30.83</weekLow52>
            <earningsPerShare>5.20149</earningsPerShare>
            <priceEarningsRatio>8.93</priceEarningsRatio>
            <beta>1.32</beta>
            <return1week>1.72</return1week>
            <return4week>1.72</return4week>
            <return3month>1.72</return3month>
            <returnYeartodate>1.72</returnYeartodate>
            <return1year>1.72</return1year>
            <return3year>1.72</return3year>
            <return5year>1.72</return5year>
            <changePercentage>-0.81162125</changePercentage>
            <sector>Financial</sector>
            <industry>Money Center Banks</industry>
            <volume>41.097679</volume>
        </Stock>
        <Stock>
            <company>Johnson &amp; Johnson</company>
            <symbol>JNJ</symbol>
            <exchange>NYSE</exchange>
            <lastPrice>72.9</lastPrice>
            <change>0.32</change>
            <quantity>101.00</quantity>
            <costBasis>7317.24</costBasis>
            <marketValue>7362.9</marketValue>
            <gain>45.66</gain>
            <gainPercentage>0.62</gainPercentage>
            <dailyGain>32.32</dailyGain>
            <overallReturn>0.62</overallReturn>
            <marketCap>202024.97</marketCap>
            <openPrice>72.88</openPrice>
            <dailyHighPrice>73.01</dailyHighPrice>
            <dailyLowPrice>72.37</dailyLowPrice>
            <averageVolume>10.849352</averageVolume>
            <weekHigh52>73.01</weekHigh52>
            <weekLow52>61.71</weekLow52>
            <earningsPerShare>3.04416</earningsPerShare>
            <priceEarningsRatio>23.95</priceEarningsRatio>
            <beta>0.54</beta>
            <return1week>0.62</return1week>
            <return4week>0.62</return4week>
            <return3month>0.62</return3month>
            <returnYeartodate>0.62</returnYeartodate>
            <return1year>0.62</return1year>
            <return3year>0.62</return3year>
            <return5year>0.62</return5year>
            <changePercentage>0.44089237</changePercentage>
            <sector>Healthcare</sector>
            <industry>Biotechnology and Drugs</industry>
            <volume>10.573077</volume>
        </Stock>
        <Stock>
            <company>Intl. Business Machines...</company>
            <symbol>IBM</symbol>
            <exchange>NYSE</exchange>
            <lastPrice>193.65</lastPrice>
            <change>1.06</change>
            <quantity>29.00</quantity>
            <costBasis>5567.98</costBasis>
            <marketValue>5615.85</marketValue>
            <gain>47.87</gain>
            <gainPercentage>0.86</gainPercentage>
            <dailyGain>30.739943</dailyGain>
            <overallReturn>0.86</overallReturn>
            <marketCap>218811.41</marketCap>
            <openPrice>193.85</openPrice>
            <dailyHighPrice>194.46</dailyHighPrice>
            <dailyLowPrice>193.24</dailyLowPrice>
            <averageVolume>3.8379359</averageVolume>
            <weekHigh52>211.79</weekHigh52>
            <weekLow52>179.5</weekLow52>
            <earningsPerShare>13.89455</earningsPerShare>
            <priceEarningsRatio>13.94</priceEarningsRatio>
            <beta>0.66</beta>
            <return1week>0.86</return1week>
            <return4week>0.86</return4week>
            <return3month>0.86</return3month>
            <returnYeartodate>0.86</returnYeartodate>
            <return1year>0.86</return1year>
            <return3year>0.86</return3year>
            <return5year>0.86</return5year>
            <changePercentage>0.55039078</changePercentage>
            <sector>Technology</sector>
            <industry>Computer Services</industry>
            <volume>3.893754</volume>
        </Stock>
        <Stock>
            <company>Intel Corporation</company>
            <symbol>INTC</symbol>
            <exchange>NASDAQ</exchange>
            <lastPrice>22.68</lastPrice>
            <change>0.57</change>
            <quantity>152.00</quantity>
            <costBasis>3356.39</costBasis>
            <marketValue>3447.36</marketValue>
            <gain>90.97</gain>
            <gainPercentage>2.71</gainPercentage>
            <dailyGain>86.64</dailyGain>
            <overallReturn>2.71</overallReturn>
            <marketCap>112855.68</marketCap>
            <openPrice>22.12</openPrice>
            <dailyHighPrice>23.06</dailyHighPrice>
            <dailyLowPrice>22.11</dailyLowPrice>
            <averageVolume>39.644512</averageVolume>
            <weekHigh52>29.27</weekHigh52>
            <weekLow52>19.23</weekLow52>
            <earningsPerShare>2.28884</earningsPerShare>
            <priceEarningsRatio>9.91</priceEarningsRatio>
            <beta>1.07</beta>
            <return1week>2.71</return1week>
            <return4week>2.71</return4week>
            <return3month>2.71</return3month>
            <returnYeartodate>2.71</returnYeartodate>
            <return1year>2.71</return1year>
            <return3year>2.71</return3year>
            <return5year>2.71</return5year>
            <changePercentage>2.5780175</changePercentage>
            <sector>Technology</sector>
            <industry>Semiconductors</industry>
            <volume>101.0196</volume>
        </Stock>
        <Stock>
            <company>Honeywell International...</company>
            <symbol>HON</symbol>
            <exchange>NYSE</exchange>
            <lastPrice>67.31</lastPrice>
            <change>0.58</change>
            <quantity>46.00</quantity>
            <costBasis>3068.41</costBasis>
            <marketValue>3096.26</marketValue>
            <gain>27.85</gain>
            <gainPercentage>0.91</gainPercentage>
            <dailyGain>26.679724</dailyGain>
            <overallReturn>0.91</overallReturn>
            <marketCap>52728.777</marketCap>
            <openPrice>67</openPrice>
            <dailyHighPrice>67.5</dailyHighPrice>
            <dailyLowPrice>66.74</dailyLowPrice>
            <averageVolume>3.4411421</averageVolume>
            <weekHigh52>67.5</weekHigh52>
            <weekLow52>52.21</weekLow52>
            <earningsPerShare>2.98392</earningsPerShare>
            <priceEarningsRatio>22.56</priceEarningsRatio>
            <beta>1.35</beta>
            <return1week>0.91</return1week>
            <return4week>0.91</return4week>
            <return3month>0.91</return3month>
            <returnYeartodate>0.91</returnYeartodate>
            <return1year>0.91</return1year>
            <return3year>0.91</return3year>
            <return5year>0.91</return5year>
            <changePercentage>0.86916554</changePercentage>
            <sector>Technology</sector>
            <industry>Scientific and Technical Instr.</industry>
            <volume>2.2703631</volume>
        </Stock>
        <Stock>
            <company>Hewlett-Packard Company</company>
            <symbol>HPQ</symbol>
            <exchange>NYSE</exchange>
            <lastPrice>17.11</lastPrice>
            <change>-0.10</change>
            <quantity>98.00</quantity>
            <costBasis>1668.35</costBasis>
            <marketValue>1676.78</marketValue>
            <gain>8.43</gain>
            <gainPercentage>0.51</gainPercentage>
            <dailyGain>-9.7998037</dailyGain>
            <overallReturn>0.51</overallReturn>
            <marketCap>33641.02</marketCap>
            <openPrice>17.25</openPrice>
            <dailyHighPrice>17.45</dailyHighPrice>
            <dailyLowPrice>17.04</dailyLowPrice>
            <averageVolume>32.2016</averageVolume>
            <weekHigh52>30</weekHigh52>
            <weekLow52>11.35</weekLow52>
            <earningsPerShare>-6.44704</earningsPerShare>
            <priceEarningsRatio>0</priceEarningsRatio>
            <beta>1.07</beta>
            <return1week>0.51</return1week>
            <return4week>0.51</return4week>
            <return3month>0.51</return3month>
            <returnYeartodate>0.51</returnYeartodate>
            <return1year>0.51</return1year>
            <return3year>0.51</return3year>
            <return5year>0.51</return5year>
            <changePercentage>-0.58104867</changePercentage>
            <sector>Technology</sector>
            <industry>Computer Hardware</industry>
            <volume>28.718933</volume>
        </Stock>
        <Stock>
            <company>General Motors Company</company>
            <symbol>GM</symbol>
            <exchange>NYSE</exchange>
            <lastPrice>29.49</lastPrice>
            <change>0.18</change>
            <quantity>68.00</quantity>
            <costBasis>2067.47</costBasis>
            <marketValue>2005.32</marketValue>
            <gain>-62.15</gain>
            <gainPercentage>-3.01</gainPercentage>
            <dailyGain>12.24</dailyGain>
            <overallReturn>-3.01</overallReturn>
            <marketCap>46181.926</marketCap>
            <openPrice>29.48</openPrice>
            <dailyHighPrice>29.65</dailyHighPrice>
            <dailyLowPrice>29.19</dailyLowPrice>
            <averageVolume>11.749952</averageVolume>
            <weekHigh52>30.68</weekHigh52>
            <weekLow52>18.72</weekLow52>
            <earningsPerShare>2.66454</earningsPerShare>
            <priceEarningsRatio>11.07</priceEarningsRatio>
            <beta>0</beta>
            <return1week>-3.01</return1week>
            <return4week>-3.01</return4week>
            <return3month>-3.01</return3month>
            <returnYeartodate>-3.01</returnYeartodate>
            <return1year>-3.01</return1year>
            <return3year>-3.01</return3year>
            <return5year>-3.01</return5year>
            <changePercentage>0.61412591</changePercentage>
            <sector>Consumer Cyclical</sector>
            <industry>Auto and Truck Manufacturers</industry>
            <volume>12.065396</volume>
        </Stock>
        <Stock>
            <company>General Electric Company</company>
            <symbol>GE</symbol>
            <exchange>NYSE</exchange>
            <lastPrice>21.3</lastPrice>
            <change>0.18</change>
            <quantity>75.00</quantity>
            <costBasis>1597.99</costBasis>
            <marketValue>1597.5</marketValue>
            <gain>-0.49</gain>
            <gainPercentage>-0.03</gainPercentage>
            <dailyGain>13.49985</dailyGain>
            <overallReturn>-0.03</overallReturn>
            <marketCap>223358.19</marketCap>
            <openPrice>21.22</openPrice>
            <dailyHighPrice>21.54</dailyHighPrice>
            <dailyLowPrice>21.12</dailyLowPrice>
            <averageVolume>42.398476</averageVolume>
            <weekHigh52>23.18</weekHigh52>
            <weekLow52>18.02</weekLow52>
            <earningsPerShare>1.34742</earningsPerShare>
            <priceEarningsRatio>15.81</priceEarningsRatio>
            <beta>1.60</beta>
            <return1week>-0.03</return1week>
            <return4week>-0.03</return4week>
            <return3month>-0.03</return3month>
            <returnYeartodate>-0.03</returnYeartodate>
            <return1year>-0.03</return1year>
            <return3year>-0.03</return3year>
            <return5year>-0.03</return5year>
            <changePercentage>0.85226512</changePercentage>
            <sector>Financial</sector>
            <industry>Consumer Financial Services</industry>
            <volume>63.8583</volume>
        </Stock>
        <Stock>
            <company>Exxon Mobil Corporation</company>
            <symbol>XOM</symbol>
            <exchange>NYSE</exchange>
            <lastPrice>90.2</lastPrice>
            <change>0.73</change>
            <quantity>92.00</quantity>
            <costBasis>8224.55</costBasis>
            <marketValue>8298.4</marketValue>
            <gain>73.85</gain>
            <gainPercentage>0.90</gainPercentage>
            <dailyGain>67.15963</dailyGain>
            <overallReturn>0.90</overallReturn>
            <marketCap>411252.69</marketCap>
            <openPrice>89.76</openPrice>
            <dailyHighPrice>90.94</dailyHighPrice>
            <dailyLowPrice>89.6</dailyLowPrice>
            <averageVolume>13.416714</averageVolume>
            <weekHigh52>93.67</weekHigh52>
            <weekLow52>77.13</weekLow52>
            <earningsPerShare>9.46932</earningsPerShare>
            <priceEarningsRatio>9.53</priceEarningsRatio>
            <beta>0.51</beta>
            <return1week>0.90</return1week>
            <return4week>0.90</return4week>
            <return3month>0.90</return3month>
            <returnYeartodate>0.90</returnYeartodate>
            <return1year>0.90</return1year>
            <return3year>0.90</return3year>
            <return5year>0.90</return5year>
            <changePercentage>0.81591117</changePercentage>
            <sector>Energy</sector>
            <industry>Oil and Gas - Integrated</industry>
            <volume>13.401388</volume>
        </Stock>
        <Stock>
            <company>E I Du Pont De Nemours...</company>
            <symbol>DD</symbol>
            <exchange>NYSE</exchange>
            <lastPrice>46.36</lastPrice>
            <change>0.39</change>
            <quantity>108.00</quantity>
            <costBasis>5006.35</costBasis>
            <marketValue>5006.88</marketValue>
            <gain>0.53</gain>
            <gainPercentage>0.01</gainPercentage>
            <dailyGain>42.119892</dailyGain>
            <overallReturn>0.01</overallReturn>
            <marketCap>43229.355</marketCap>
            <openPrice>46.27</openPrice>
            <dailyHighPrice>46.49</dailyHighPrice>
            <dailyLowPrice>46.19</dailyLowPrice>
            <averageVolume>5.6473761</averageVolume>
            <weekHigh52>57.5</weekHigh52>
            <weekLow52>41.67</weekLow52>
            <earningsPerShare>2.98126</earningsPerShare>
            <priceEarningsRatio>15.55</priceEarningsRatio>
            <beta>1.46</beta>
            <return1week>0.01</return1week>
            <return4week>0.01</return4week>
            <return3month>0.01</return3month>
            <returnYeartodate>0.01</returnYeartodate>
            <return1year>0.01</return1year>
            <return3year>0.01</return3year>
            <return5year>0.01</return5year>
            <changePercentage>0.848378</changePercentage>
            <sector>Basic Materials</sector>
            <industry>Chemical Manufacturing</industry>
            <volume>4.8597832</volume>
        </Stock>
        <Stock>
            <company>Citigroup Inc.</company>
            <symbol>C</symbol>
            <exchange>NYSE</exchange>
            <lastPrice>41.24</lastPrice>
            <change>-1.24</change>
            <quantity>120.00</quantity>
            <costBasis>5037.19</costBasis>
            <marketValue>4948.8</marketValue>
            <gain>-88.39</gain>
            <gainPercentage>-1.75</gainPercentage>
            <dailyGain>-148.79976</dailyGain>
            <overallReturn>-1.75</overallReturn>
            <marketCap>120937.16</marketCap>
            <openPrice>41.53</openPrice>
            <dailyHighPrice>41.62</dailyHighPrice>
            <dailyLowPrice>40.9</dailyLowPrice>
            <averageVolume>38.078209</averageVolume>
            <weekHigh52>43.25</weekHigh52>
            <weekLow52>24.61</weekLow52>
            <earningsPerShare>2.37965</earningsPerShare>
            <priceEarningsRatio>17.33</priceEarningsRatio>
            <beta>2.58</beta>
            <return1week>-1.75</return1week>
            <return4week>-1.75</return4week>
            <return3month>-1.75</return3month>
            <returnYeartodate>-1.75</returnYeartodate>
            <return1year>-1.75</return1year>
            <return3year>-1.75</return3year>
            <return5year>-1.75</return5year>
            <changePercentage>-2.9190156</changePercentage>
            <sector>Financial</sector>
            <industry>Money Center Banks</industry>
            <volume>80.186546</volume>
        </Stock>
        <Stock>
            <company>Caterpillar Inc.</company>
            <symbol>CAT</symbol>
            <exchange>NYSE</exchange>
            <lastPrice>95.7</lastPrice>
            <change>0.51</change>
            <quantity>45.00</quantity>
            <costBasis>4259.44</costBasis>
            <marketValue>4306.5</marketValue>
            <gain>47.06</gain>
            <gainPercentage>1.10</gainPercentage>
            <dailyGain>22.949776</dailyGain>
            <overallReturn>1.10</overallReturn>
            <marketCap>62581.449</marketCap>
            <openPrice>95.71</openPrice>
            <dailyHighPrice>96.2899</dailyHighPrice>
            <dailyLowPrice>95.09</dailyLowPrice>
            <averageVolume>5.770082</averageVolume>
            <weekHigh52>116.95</weekHigh52>
            <weekLow52>78.25</weekLow52>
            <earningsPerShare>9.76772</earningsPerShare>
            <priceEarningsRatio>9.80</priceEarningsRatio>
            <beta>1.87</beta>
            <return1week>1.10</return1week>
            <return4week>1.10</return4week>
            <return3month>1.10</return3month>
            <returnYeartodate>1.10</returnYeartodate>
            <return1year>1.10</return1year>
            <return3year>1.10</return3year>
            <return5year>1.10</return5year>
            <changePercentage>0.53576475</changePercentage>
            <sector>Capital Goods</sector>
            <industry>Constr. and Agric. Machinery</industry>
            <volume>4.8255382</volume>
        </Stock>
        <Stock>
            <company>The Boeing Company</company>
            <symbol>BA</symbol>
            <exchange>NYSE</exchange>
            <lastPrice>75.26</lastPrice>
            <change>0.92</change>
            <quantity>45.00</quantity>
            <costBasis>3449.44</costBasis>
            <marketValue>3386.7</marketValue>
            <gain>-62.74</gain>
            <gainPercentage>-1.82</gainPercentage>
            <dailyGain>41.400269</dailyGain>
            <overallReturn>-1.82</overallReturn>
            <marketCap>56751.828</marketCap>
            <openPrice>72.78</openPrice>
            <dailyHighPrice>75.63</dailyHighPrice>
            <dailyLowPrice>72.68</dailyLowPrice>
            <averageVolume>6.0106788</averageVolume>
            <weekHigh52>78.02</weekHigh52>
            <weekLow52>66.82</weekLow52>
            <earningsPerShare>5.66873</earningsPerShare>
            <priceEarningsRatio>13.28</priceEarningsRatio>
            <beta>1.21</beta>
            <return1week>-1.82</return1week>
            <return4week>-1.82</return4week>
            <return3month>-1.82</return3month>
            <returnYeartodate>-1.82</returnYeartodate>
            <return1year>-1.82</return1year>
            <return3year>-1.82</return3year>
            <return5year>-1.82</return5year>
            <changePercentage>1.237565</changePercentage>
            <sector>Capital Goods</sector>
            <industry>Aerospace and Defense</industry>
            <volume>21.867123</volume>
        </Stock>
        <Stock>
            <company>Goldman Sachs Group...</company>
            <symbol>GS</symbol>
            <exchange>NYSE</exchange>
            <lastPrice>141.01</lastPrice>
            <change>-0.08</change>
            <quantity>55.00</quantity>
            <costBasis>7475.24</costBasis>
            <marketValue>7755.55</marketValue>
            <gain>280.31</gain>
            <gainPercentage>3.75</gainPercentage>
            <dailyGain>-4.40011</dailyGain>
            <overallReturn>3.75</overallReturn>
            <marketCap>66266.75</marketCap>
            <openPrice>140.89</openPrice>
            <dailyHighPrice>141.95</dailyHighPrice>
            <dailyLowPrice>139.62</dailyLowPrice>
            <averageVolume>4.2686939</averageVolume>
            <weekHigh52>141.95</weekHigh52>
            <weekLow52>90.43</weekLow52>
            <earningsPerShare>14.15781</earningsPerShare>
            <priceEarningsRatio>9.96</priceEarningsRatio>
            <beta>1.38</beta>
            <return1week>3.75</return1week>
            <return4week>3.75</return4week>
            <return3month>3.75</return3month>
            <returnYeartodate>3.75</returnYeartodate>
            <return1year>3.75</return1year>
            <return3year>3.75</return3year>
            <return5year>3.75</return5year>
            <changePercentage>-0.056702696</changePercentage>
            <sector>Financial</sector>
            <industry>Money Center Banks</industry>
            <volume>6.5960622</volume>
        </Stock>
        <Stock>
            <company>American Intl. Group...</company>
            <symbol>AIG</symbol>
            <exchange>NYSE</exchange>
            <lastPrice>35.21</lastPrice>
            <change>-0.33</change>
            <quantity>150.00</quantity>
            <costBasis>5241.49</costBasis>
            <marketValue>5281.5</marketValue>
            <gain>40.01</gain>
            <gainPercentage>0.76</gainPercentage>
            <dailyGain>-49.5003</dailyGain>
            <overallReturn>0.76</overallReturn>
            <marketCap>51980.68</marketCap>
            <openPrice>35.57</openPrice>
            <dailyHighPrice>35.81</dailyHighPrice>
            <dailyLowPrice>35.1401</dailyLowPrice>
            <averageVolume>30.231457</averageVolume>
            <weekHigh52>37.67</weekHigh52>
            <weekLow52>24.1602</weekLow52>
            <earningsPerShare>14.40778</earningsPerShare>
            <priceEarningsRatio>2.44</priceEarningsRatio>
            <beta>3.45</beta>
            <return1week>0.76</return1week>
            <return4week>0.76</return4week>
            <return3month>0.76</return3month>
            <returnYeartodate>0.76</returnYeartodate>
            <return1year>0.76</return1year>
            <return3year>0.76</return3year>
            <return5year>0.76</return5year>
            <changePercentage>-0.92853636</changePercentage>
            <sector>Financial</sector>
            <industry>Insurance (Prop. and Casualty)</industry>
            <volume>17.737146</volume>
        </Stock>
        <Stock>
            <company>American Express Company</company>
            <symbol>AXP</symbol>
            <exchange>NYSE</exchange>
            <lastPrice>60.74</lastPrice>
            <change>0.12</change>
            <quantity>60.00</quantity>
            <costBasis>3628.99</costBasis>
            <marketValue>3644.4</marketValue>
            <gain>15.41</gain>
            <gainPercentage>0.42</gainPercentage>
            <dailyGain>7.20018</dailyGain>
            <overallReturn>0.42</overallReturn>
            <marketCap>67971.836</marketCap>
            <openPrice>61.1</openPrice>
            <dailyHighPrice>61.2</dailyHighPrice>
            <dailyLowPrice>60.58</dailyLowPrice>
            <averageVolume>5.3631</averageVolume>
            <weekHigh52>61.97</weekHigh52>
            <weekLow52>48.84</weekLow52>
            <earningsPerShare>4.32012</earningsPerShare>
            <priceEarningsRatio>14.06</priceEarningsRatio>
            <beta>1.82</beta>
            <return1week>0.42</return1week>
            <return4week>0.42</return4week>
            <return3month>0.42</return3month>
            <returnYeartodate>0.42</returnYeartodate>
            <return1year>0.42</return1year>
            <return3year>0.42</return3year>
            <return5year>0.42</return5year>
            <changePercentage>0.197959</changePercentage>
            <sector>Financial</sector>
            <industry>Regional Banks</industry>
            <volume>4.6888771</volume>
        </Stock>
        <Stock>
            <company>Altria Group, Inc.</company>
            <symbol>MO</symbol>
            <exchange>NYSE</exchange>
            <lastPrice>32.99</lastPrice>
            <change>0.21</change>
            <quantity>110.00</quantity>
            <costBasis>3634.59</costBasis>
            <marketValue>3628.9</marketValue>
            <gain>-5.69</gain>
            <gainPercentage>-0.16</gainPercentage>
            <dailyGain>23.10033</dailyGain>
            <overallReturn>-0.16</overallReturn>
            <marketCap>66808.25</marketCap>
            <openPrice>32.93</openPrice>
            <dailyHighPrice>33.1</dailyHighPrice>
            <dailyLowPrice>32.74</dailyLowPrice>
            <averageVolume>10.424899</averageVolume>
            <weekHigh52>36.29</weekHigh52>
            <weekLow52>28</weekLow52>
            <earningsPerShare>1.91975</earningsPerShare>
            <priceEarningsRatio>17.18</priceEarningsRatio>
            <beta>0.45</beta>
            <return1week>-0.16</return1week>
            <return4week>-0.16</return4week>
            <return3month>-0.16</return3month>
            <returnYeartodate>-0.16</returnYeartodate>
            <return1year>-0.16</return1year>
            <return3year>-0.16</return3year>
            <return5year>-0.16</return5year>
            <changePercentage>0.64064342</changePercentage>
            <sector>Consumer/Non-Cyclical</sector>
            <industry>Tobacco</industry>
            <volume>7.292685</volume>
        </Stock>
        <Stock>
            <company>Alcoa Inc.</company>
            <symbol>AA</symbol>
            <exchange>NYSE</exchange>
            <lastPrice>8.94</lastPrice>
            <change>0.06</change>
            <quantity>1500.00</quantity>
            <costBasis>13324.99</costBasis>
            <marketValue>13410</marketValue>
            <gain>85.01</gain>
            <gainPercentage>0.64</gainPercentage>
            <dailyGain>89.9985</dailyGain>
            <overallReturn>0.64</overallReturn>
            <marketCap>9540.874</marketCap>
            <openPrice>8.92</openPrice>
            <dailyHighPrice>8.99</dailyHighPrice>
            <dailyLowPrice>8.9</dailyLowPrice>
            <averageVolume>17.97714</averageVolume>
            <weekHigh52>10.92</weekHigh52>
            <weekLow52>7.9661</weekLow52>
            <earningsPerShare>0.15684</earningsPerShare>
            <priceEarningsRatio>57.00</priceEarningsRatio>
            <beta>2.05</beta>
            <return1week>0.64</return1week>
            <return4week>0.64</return4week>
            <return3month>0.64</return3month>
            <returnYeartodate>0.64</returnYeartodate>
            <return1year>0.64</return1year>
            <return3year>0.64</return3year>
            <return5year>0.64</return5year>
            <changePercentage>0.67566967</changePercentage>
            <sector>Basic Materials</sector>
            <industry>Metal Mining</industry>
            <volume>17.858358</volume>
        </Stock>
        <Stock>
            <company>3M Co</company>
            <symbol>MMM</symbol>
            <exchange>NYSE</exchange>
            <lastPrice>98.08</lastPrice>
            <change>0.48</change>
            <quantity>80.00</quantity>
            <costBasis>7766.39</costBasis>
            <marketValue>7846.4</marketValue>
            <gain>80.01</gain>
            <gainPercentage>1.03</gainPercentage>
            <dailyGain>38.400242</dailyGain>
            <overallReturn>1.03</overallReturn>
            <marketCap>67864.617</marketCap>
            <openPrice>97.79</openPrice>
            <dailyHighPrice>98.5</dailyHighPrice>
            <dailyLowPrice>97.51</dailyLowPrice>
            <averageVolume>2.720767</averageVolume>
            <weekHigh52>98.5</weekHigh52>
            <weekLow52>81.985</weekLow52>
            <earningsPerShare>6.2539</earningsPerShare>
            <priceEarningsRatio>15.68</priceEarningsRatio>
            <beta>0.87</beta>
            <return1week>1.03</return1week>
            <return4week>1.03</return4week>
            <return3month>1.03</return3month>
            <returnYeartodate>1.03</returnYeartodate>
            <return1year>1.03</return1year>
            <return3year>1.03</return3year>
            <return5year>1.03</return5year>
            <changePercentage>0.49180672</changePercentage>
            <sector>Capital Goods</sector>
            <industry>Constr. - Supplies and Fixtures</industry>
            <volume>2.8043549</volume>
        </Stock>
    </data>
</MarketData>
